piwikapi/__init__.py
piwikapi/analytics.py
piwikapi/exceptions.py
piwikapi/tracking.py
piwikapi/plugins/__init__.py
piwikapi/plugins/goals.py
piwikapi/tests/__init__.py
piwikapi/tests/__main__.py
piwikapi/tests/analytics.py
piwikapi/tests/base.py
piwikapi/tests/ecommerce.py
piwikapi/tests/goals.py
piwikapi/tests/request.py
piwikapi/tests/test_analytics.py
piwikapi/tests/test_ecommerce.py
piwikapi/tests/test_goals.py
piwikapi/tests/test_tracking.py
piwikapi/tests/tracking.py
piwikapi_drred-0.4.1.dist-info/DESCRIPTION.rst
piwikapi_drred-0.4.1.dist-info/METADATA
piwikapi_drred-0.4.1.dist-info/RECORD
piwikapi_drred-0.4.1.dist-info/WHEEL
piwikapi_drred-0.4.1.dist-info/metadata.json
piwikapi_drred-0.4.1.dist-info/top_level.txt
