Metadata-Version: 2.0
Name: piwikapi-drred
Version: 0.4.1
Summary: Python Piwik API
Home-page: https://github.com/piwik/piwik-python-api
Author: Nicolas Kuttler, Hanxue Lee
Author-email: pypi@kuttler.eu, hanxue@users.noreply.github.com
License: BSD
Platform: UNKNOWN
Classifier: Development Status :: 4 - Beta
Classifier: Environment :: Web Environment
Classifier: Intended Audience :: Developers
Classifier: License :: OSI Approved :: BSD License
Classifier: Operating System :: OS Independent
Classifier: Programming Language :: Python
Classifier: Programming Language :: Python :: 2
Classifier: Programming Language :: Python :: 2.5
Classifier: Programming Language :: Python :: 2.6
Classifier: Programming Language :: Python :: 2.7
Classifier: Programming Language :: Python :: 3
Classifier: Programming Language :: Python :: 3.2
Classifier: Programming Language :: Python :: 3.3
Provides-Extra: Python 2.5
Requires-Dist: simplejson; extra == 'Python 2.5'
